AUTHORS
ChangeLog
LICENSE
README.md
RELEASE.md
requirements.txt
setup.cfg
setup.py
clank/__init__.py
clank/base.py
clank/errors.py
clank/manager.py
clank.egg-info/PKG-INFO
clank.egg-info/SOURCES.txt
clank.egg-info/dependency_links.txt
clank.egg-info/not-zip-safe
clank.egg-info/pbr.json
clank.egg-info/requires.txt
clank.egg-info/top_level.txt