Metadata-Version: 1.1
Name: clank
Version: v0.1.1
Summary: A library to quickly build monolithic commandline tools.
Home-page: UNKNOWN
Author: Ryan Bourgeois
Author-email: bluedragonx@gmail.com
License: BSD-Modified
Keywords: cli console
Platform: UNKNOWN
Classifier: Environment :: Console
Classifier: Intended Audience :: Developers
Classifier: License :: OSI Approved :: BSD License
Classifier: Programming Language :: Python :: 2
